{
    "time": "2022/05/08, 21:18:41.274530",
    "last_login": "2022/04/30, 15:58:55.979251",
    "last_location": "location_a",
    "cash": 51793.5,
    "businesses": {
        "location_a": {
            "street_food": {
                "date_acquired": "2022/04/30, 14:06:29.274530",
                "type": "buko_stall",
                "ownership": true,
                "is_open": false,
                "open_until": "",
                "has_employee": false,
                "sales": 0,
                "lifetime_sales": 5248.75,
                "last_profit": 80.25,
                "lifetime_profit": 2248.75,
                "current_operation_sales": 280.25
            },
            "sari_sari_store": {
                "date_acquired": "2022/04/30, 14:07:16.609370",
                "ownership": true,
                "is_open": false,
                "open_until": "",
                "has_employee": false,
                "sales": 0,
                "lifetime_sales": 19228.0,
                "last_profit": 439.0,
                "lifetime_profit": 10228.0,
                "current_operation_sales": 1039.0
            },
            "ukay_ukay": {
                "date_acquired": "2022/04/30, 14:07:18.693172",
                "ownership": true,
                "is_open": false,
                "open_until": "",
                "has_employee": false,
                "sales": 0,
                "lifetime_sales": 37890.0,
                "last_profit": 1687.5,
                "lifetime_profit": 17890.0,
                "current_operation_sales": 2937.5
            },
            "food_cart": {
                "date_acquired": "2022/04/30, 14:23:43.283936",
                "ownership": true,
                "is_open": false,
                "open_until": "",
                "has_employee": false,
                "sales": 0,
                "lifetime_sales": 43826.75,
                "last_profit": 2244.5,
                "lifetime_profit": 26226.75,
                "current_operation_sales": 3844.5
            }
        }
    }
}